wifidroid/__init__.py
wifidroid/wifi.py
wifidroid-0.0.1.dist-info/LICENSE
wifidroid-0.0.1.dist-info/METADATA
wifidroid-0.0.1.dist-info/WHEEL
wifidroid-0.0.1.dist-info/top_level.txt
wifidroid-0.0.1.dist-info/RECORD
