Metadata-Version: 2.1
Name: wifidroid
Version: 0.0.1
Summary: Module created for Wi-Fi management in Android
Home-page: https://github.com/yaxter/wifidroid
Author: Edilson Pineda
Author-email: edilsonpineda011@gmail.com
License: UNKNOWN
Keywords: wifi android kivy kivymd Android Wi-Fi python-for-android python
Platform: UNKNOWN
Classifier: Programming Language :: Python :: 3
Classifier: License :: OSI Approved :: MIT License
Classifier: Operating System :: Android
Requires-Python: >=3
Requires-Dist: pyjnius
